caiyun/__init__.py
caiyun/cli.py
caiyun-0.1.3.dist-info/DESCRIPTION.rst
caiyun-0.1.3.dist-info/METADATA
caiyun-0.1.3.dist-info/RECORD
caiyun-0.1.3.dist-info/WHEEL
caiyun-0.1.3.dist-info/entry_points.txt
caiyun-0.1.3.dist-info/metadata.json
caiyun-0.1.3.dist-info/top_level.txt
