Metadata-Version: 2.0
Name: caiyun
Version: 0.1.3
Summary: Zimuzu resources to Baidu Yun Pan
Home-page: https://github.com/messense/caiyun
Author: Messense Lv
Author-email: messense@icloud.com
License: UNKNOWN
Keywords: zimuzu,baidu
Platform: UNKNOWN
Requires-Dist: Pillow
Requires-Dist: baidupcsapi
Requires-Dist: click
Requires-Dist: lxml
Requires-Dist: requests
